setup.py
djan_dsnd_probability/Binomialdistribution.py
djan_dsnd_probability/Gaussiandistribution.py
djan_dsnd_probability/Generaldistribution.py
djan_dsnd_probability/__init__.py
djan_dsnd_probability.egg-info/PKG-INFO
djan_dsnd_probability.egg-info/SOURCES.txt
djan_dsnd_probability.egg-info/dependency_links.txt
djan_dsnd_probability.egg-info/not-zip-safe
djan_dsnd_probability.egg-info/top_level.txt