Metadata-Version: 1.0
Name: djan-dsnd-probability
Version: 0.1
Summary: Gaussian and Binomial distributions
Home-page: UNKNOWN
Author: Djan Magno
Author-email: djan.magno@gmail.com
License: UNKNOWN
Platform: UNKNOWN
